HDLpy/__init__.py
HDLpy/base/Signal.py
HDLpy/base/__init__.py
HDLpy/base/block.py
HDLpy/compile/__init__.py
HDLpy/compile/code.py
HDLpy/compile/compile.py
HDLpy/output/__init__.py
HDLpy/output/utils.py
HDLpy/output/write_vcd.py
HDLpy/output/write_wavedrom.py
SystemPy/__init__.py
SystemPy/test.py
SystemPy/test1.py
SystemPy/base/Signal.py
SystemPy/base/__init__.py
SystemPy/base/block.py
SystemPy/base/save_wave.py
SystemPy/compile/__init__.py
SystemPy/compile/code.py
SystemPy/compile/compile.py
SystemPy/output/__init__.py
SystemPy/output/utils.py
SystemPy/output/write_vcd.py
SystemPy/output/write_wavedrom.py
HDLpy-1.0.0.dist-info/METADATA
HDLpy-1.0.0.dist-info/WHEEL
HDLpy-1.0.0.dist-info/top_level.txt
HDLpy-1.0.0.dist-info/RECORD
