Metadata-Version: 2.1
Name: HDLpy
Version: 1.0.0
Summary: HDLpy
Author: ChenHaha
Author-email: 596838981@qq.com
License: Apache2.0
Requires-Dist: requests
Requires-Dist: tqdm
Requires-Dist: pyvcd
